hdx/scraper/framework/__init__.py
hdx/scraper/framework/_version.py
hdx/scraper/framework/base_scraper.py
hdx/scraper/framework/runner.py
hdx/scraper/framework/outputs/__init__.py
hdx/scraper/framework/outputs/base.py
hdx/scraper/framework/outputs/excelfile.py
hdx/scraper/framework/outputs/googlesheets.py
hdx/scraper/framework/outputs/json.py
hdx/scraper/framework/scrapers/__init__.py
hdx/scraper/framework/scrapers/aggregator.py
hdx/scraper/framework/scrapers/configurable_scraper.py
hdx/scraper/framework/scrapers/resource_downloader.py
hdx/scraper/framework/scrapers/rowparser.py
hdx/scraper/framework/scrapers/timeseries.py
hdx/scraper/framework/utilities/__init__.py
hdx/scraper/framework/utilities/fallbacks.py
hdx/scraper/framework/utilities/hapi_admins.py
hdx/scraper/framework/utilities/lookup.py
hdx/scraper/framework/utilities/org_type.py
hdx/scraper/framework/utilities/org_type_configuration.yaml
hdx/scraper/framework/utilities/reader.py
hdx/scraper/framework/utilities/region_lookup.py
hdx/scraper/framework/utilities/sector.py
hdx/scraper/framework/utilities/sector_configuration.yaml
hdx/scraper/framework/utilities/sources.py
hdx/scraper/framework/utilities/writer.py
hdx_python_scraper-2.7.1.dist-info/METADATA
hdx_python_scraper-2.7.1.dist-info/WHEEL
hdx_python_scraper-2.7.1.dist-info/licenses/LICENSE
hdx_python_scraper-2.7.1.dist-info/RECORD
