Metadata-Version: 2.4
Name: hdx-python-scraper
Version: 2.7.1
Summary: HDX Python scraper utilities to assemble data from multiple sources
Project-URL: Homepage, https://github.com/OCHA-DAP/hdx-python-scraper
Author-email: Michael Rans <rans@email.com>
License: MIT
License-File: LICENSE
Keywords: HDX,data assembly,data transformation,scrapers,tabular data
Classifier: Development Status :: 5 - Production/Stable
Classifier: Intended Audience :: Developers
Classifier: License :: OSI Approved :: MIT License
Classifier: Natural Language :: English
Classifier: Operating System :: MacOS
Classifier: Operating System :: Microsoft :: Windows
Classifier: Operating System :: POSIX :: Linux
Classifier: Operating System :: Unix
Classifier: Programming Language :: Python
Classifier: Programming Language :: Python :: 3
Classifier: Programming Language :: Python :: 3 :: Only
Classifier: Programming Language :: Python :: 3.8
Classifier: Programming Language :: Python :: 3.9
Classifier: Programming Language :: Python :: 3.10
Classifier: Programming Language :: Python :: 3.11
Classifier: Programming Language :: Python :: 3.12
Classifier: Topic :: Software Development :: Libraries :: Python Modules
Requires-Python: >=3.10
Requires-Dist: gspread
Requires-Dist: hdx-python-api>=6.6.1
Requires-Dist: hdx-python-country>=4.0.1
Requires-Dist: hdx-python-utilities>=4.0.2
Requires-Dist: regex
Provides-Extra: dev
Requires-Dist: pre-commit; extra == 'dev'
Provides-Extra: docs
Requires-Dist: mkapi; extra == 'docs'
Provides-Extra: pandas
Requires-Dist: pandas>=2.2.3; extra == 'pandas'
Provides-Extra: test
Requires-Dist: pandas>=2.2.3; extra == 'test'
Requires-Dist: pytest; extra == 'test'
Requires-Dist: pytest-cov; extra == 'test'
